delphai_ml_utils/__init__.py
delphai_ml_utils/asymmetric_loss.py
delphai_ml_utils/augmentation.py
delphai_ml_utils/blobs.py
delphai_ml_utils/colab_automation.py
delphai_ml_utils/colab_integration.py
delphai_ml_utils/config.py
delphai_ml_utils/dashboards.py
delphai_ml_utils/db.py
delphai_ml_utils/deboilerplating.py
delphai_ml_utils/google_sheet.py
delphai_ml_utils/labels.py
delphai_ml_utils/multilabel_evaluation.py
delphai_ml_utils/onnx.py
delphai_ml_utils/plot_functions.py
delphai_ml_utils/scraped_web_pages.py
delphai_ml_utils/text_chunking.py
delphai_ml_utils/text_processing.py
delphai_ml_utils/transformer_helpers.py
delphai_ml_utils-1.1.0.dist-info/METADATA
delphai_ml_utils-1.1.0.dist-info/WHEEL
delphai_ml_utils-1.1.0.dist-info/RECORD
