Metadata-Version: 2.1
Name: delphai-ml-utils
Version: 1.1.0
Summary: A Python package to manage delphai machine learning operations.
Home-page: https://github.com/delphai/delphai-ml-utils
Author: ml-team-delphai
Author-email: ml@delphai.com
Requires-Python: >=3.9,<4
Classifier: Programming Language :: Python :: 3
Classifier: Programming Language :: Python :: 3.9
Classifier: Programming Language :: Python :: 3.10
Classifier: Programming Language :: Python :: 3.11
Classifier: Programming Language :: Python :: 3.12
Provides-Extra: config
Provides-Extra: database
Provides-Extra: transformers
Requires-Dist: azure-storage-blob (>=12.14.1,<13.0.0)
Requires-Dist: clean-text[gpl] (>=0.6.0,<0.7.0)
Requires-Dist: coloredlogs (>=14.0,<15.0) ; extra == "config"
Requires-Dist: confuse (>=2.0.0,<3.0.0)
Requires-Dist: dacite (>=1.6.0,<2.0.0) ; extra == "config"
Requires-Dist: deepmerge (>=0.1.0,<0.2.0) ; extra == "config"
Requires-Dist: dvc (>=3.18.0,<4.0.0)
Requires-Dist: dvc-azure (>=2.22.1,<3.0.0)
Requires-Dist: gitpython (>=3.1.34,<4.0.0)
Requires-Dist: google (>=3.0.0,<4.0.0)
Requires-Dist: goose3 (>=3.1.12,<4.0.0)
Requires-Dist: gspread (>=5.7.1,<6.0.0)
Requires-Dist: httpx (>=0.27.2,<0.28.0)
Requires-Dist: justext (>=3.0.0,<4.0.0)
Requires-Dist: keyring (>=21.5.0,<22.0.0) ; extra == "config"
Requires-Dist: kubernetes (>=12.0.0,<13.0.0) ; extra == "config"
Requires-Dist: matplotlib (>=3.2.2,<4.0.0)
Requires-Dist: memoization (>=0.3.1,<0.4.0) ; extra == "config"
Requires-Dist: mlcm (>=0.0.1,<0.0.2)
Requires-Dist: mlflow (==2.3.2)
Requires-Dist: motor (>=2.3.0,<3.0.0) ; extra == "database"
Requires-Dist: mylib (>=0.0.1,<0.0.2)
Requires-Dist: nlpaug (>=1.1.11,<2.0.0) ; extra == "transformers"
Requires-Dist: nltk (>=3.7,<4.0)
Requires-Dist: numpy (>=1.21.1,<2.0.0)
Requires-Dist: omegaconf (>=2.1.0,<3.0.0) ; extra == "config"
Requires-Dist: pandas (>=1.3.5,<2.0.0)
Requires-Dist: protobuf (<3.21.0) ; extra == "transformers"
Requires-Dist: pysbd (>=0.3.4,<0.4.0)
Requires-Dist: python-dotenv (>=1.0.0,<2.0.0)
Requires-Dist: sacremoses (>=0.0.53,<0.0.54) ; extra == "transformers"
Requires-Dist: scikit-learn (>=1.0.2,<2.0.0)
Requires-Dist: seaborn (>=0.12.1,<0.13.0)
Requires-Dist: sentencepiece (>=0.1.97,<0.2.0) ; extra == "transformers"
Requires-Dist: tldextract (>=3.4.0,<4.0.0)
Requires-Dist: torch (>=1.12.0,<1.13.0) ; extra == "transformers"
Requires-Dist: torchaudio (>=0.12.0,<0.13.0) ; extra == "transformers"
Requires-Dist: torchvision (>=0.13.0,<0.14.0) ; extra == "transformers"
Requires-Dist: tqdm (>=4.64.1,<5.0.0)
Requires-Dist: trafilatura (>=1.4.0,<2.0.0)
Requires-Dist: transformers[onnx] (>=4.24.0,<5.0.0) ; extra == "transformers"
